ptcpy/__init__.py
ptcpy/ptcpy.py
ptcpy-2.2.2.dist-info/METADATA
ptcpy-2.2.2.dist-info/WHEEL
ptcpy-2.2.2.dist-info/RECORD
