Metadata-Version: 2.1
Name: ptcpy
Version: 2.2.2
Summary: PTC Python
License: N/A
Author: Erlend Leiknes
Requires-Python: >=3.10,<4.0
Classifier: License :: Other/Proprietary License
Classifier: Programming Language :: Python :: 3
Classifier: Programming Language :: Python :: 3.10
Classifier: Programming Language :: Python :: 3.11
Classifier: Programming Language :: Python :: 3.12
